tmpauthenticator/__init__.py
jupyterhub_tmpauthenticator-1.0.0.dist-info/LICENSE
jupyterhub_tmpauthenticator-1.0.0.dist-info/METADATA
jupyterhub_tmpauthenticator-1.0.0.dist-info/WHEEL
jupyterhub_tmpauthenticator-1.0.0.dist-info/entry_points.txt
jupyterhub_tmpauthenticator-1.0.0.dist-info/top_level.txt
jupyterhub_tmpauthenticator-1.0.0.dist-info/RECORD
