Metadata-Version: 2.1
Name: jupyterhub-tmpauthenticator
Version: 1.0.0
Summary: JupyterHub authenticator that hands out temporary accounts for everyone
Home-page: https://github.com/jupyterhub/tmpauthenticator
Author: Project Jupyter Contributors
Author-email: jupyter@googlegroups.com
License: 3 Clause BSD
Requires-Python: >=3.8
License-File: LICENSE
Provides-Extra: test
Requires-Dist: aiohttp ; extra == 'test'
Requires-Dist: pytest ; extra == 'test'
Requires-Dist: pytest-asyncio ; extra == 'test'
Requires-Dist: pytest-cov ; extra == 'test'
Requires-Dist: pytest-jupyterhub ; extra == 'test'
